{
	"controllerOptions": {
		"longFormConsoleLogging": true, 
		"defaultLogLevel": "trace", 
		"deviceIdPrefix": "tv", 
		"showUserErrorMessageUI": true, 
		"networkLogLevel": "trace", 
		"deviceIdNamespace": "ts-tv"
	}, 
	"description": "Live Preview", 
	"serviceUrlPreset": "aws_edge",
	"serviceUrls" : {
		"layoutService": "https://layout-service-edge.platform.2immerse.eu/layout/v3",
		"websocketService": "https://websocket-service-edge.platform.2immerse.eu/",
		"timelineService": "https://timeline-service-edge.platform.2immerse.eu/timeline/v1"
	},
	"serviceInput": {
		"timeline": "filled-in-dynamically", 
		"layout": "filled-in-dynamically"
	},

	"debugOptions": {
		"debugComponent": true, 
		"devLogging": true, 
		"failurePlaceholders": true
	}, 
	"mode": "tv"
}
